requests_kerberos/__init__.py
requests_kerberos/exceptions.py
requests_kerberos/kerberos_.py
requests_kerberos-0.14.0.dist-info/AUTHORS
requests_kerberos-0.14.0.dist-info/LICENSE
requests_kerberos-0.14.0.dist-info/METADATA
requests_kerberos-0.14.0.dist-info/WHEEL
requests_kerberos-0.14.0.dist-info/top_level.txt
requests_kerberos-0.14.0.dist-info/RECORD
