Metadata-Version: 2.1
Name: requests-kerberos
Version: 0.14.0
Summary: A Kerberos authentication handler for python-requests
Home-page: https://github.com/requests/requests-kerberos
Author: Ian Cordasco, Cory Benfield, Michael Komitee
Author-email: graffatcolmingov@gmail.com
License: ISC License
Platform: UNKNOWN
Classifier: License :: OSI Approved :: ISC License (ISCL)
Requires-Python: >=3.6
License-File: LICENSE
License-File: AUTHORS
